hookandlook/__init__.py
hookandlook/hooks.py
hookandlook/utils.py
hookandlook/watch.py
hookandlook-0.0.3.dist-info/LICENSE
hookandlook-0.0.3.dist-info/METADATA
hookandlook-0.0.3.dist-info/WHEEL
hookandlook-0.0.3.dist-info/top_level.txt
hookandlook-0.0.3.dist-info/RECORD
